EasyGenerators/__init__.py
EasyGenerators/generators.py
EasyGenerators-0.0.2.dist-info/LICENSE
EasyGenerators-0.0.2.dist-info/METADATA
EasyGenerators-0.0.2.dist-info/WHEEL
EasyGenerators-0.0.2.dist-info/top_level.txt
EasyGenerators-0.0.2.dist-info/RECORD
