Metadata-Version: 2.1
Name: EasyGenerators
Version: 0.0.2
Summary: A powerful package of python generators
Home-page: https://github.com/ProjectsWithPython/EasyGenerators
Author: Haider Ali
Author-email: ali075398@example.com
License: UNKNOWN
Project-URL: Bug Tracker, https://github.com/ProjectsWithPython/EasyGenerators/issues
Platform: UNKNOWN
Classifier: Programming Language :: Python :: 3
Classifier: License :: OSI Approved :: MIT License
Classifier: Operating System :: OS Independent
Requires-Python: >=3.6
License-File: LICENSE
